{
  "sections": {
    "f5cf29cf-32b2-4521-a27a-9d8f87cc9c84": {
      "type": "image-banner",
      "disabled": true,
      "settings": {
        "image": "shopify:\/\/shop_images\/2974ad4a3d8f8089c0332e127ee1f465.jpg",
        "image_overlay_opacity": 0,
        "image_height": "small",
        "desktop_content_position": "middle-center",
        "show_text_box": true,
        "desktop_content_alignment": "center",
        "color_scheme": "",
        "image_behavior": "none",
        "mobile_content_alignment": "center",
        "stack_images_on_mobile": true,
        "show_text_below": true
      }
    },
    "main": {
      "type": "main-page",
      "settings": {
        "padding_top": 36,
        "padding_bottom": 0
      }
    },
    "2562b313-56ee-4fcc-b0fd-a28cdaf46732": {
      "type": "section-faq-tabs",
      "settings": {
        "padding_top": 0,
        "padding_bottom": 80
      }
    }
  },
  "order": [
    "f5cf29cf-32b2-4521-a27a-9d8f87cc9c84",
    "main",
    "2562b313-56ee-4fcc-b0fd-a28cdaf46732"
  ]
}
